gdax/__init__.py
gdax/coinbase_exchange_auth.py
gdax/private_client.py
gdax/public_client.py
gdax_api-1.2.0.dev1.dist-info/DESCRIPTION.rst
gdax_api-1.2.0.dev1.dist-info/METADATA
gdax_api-1.2.0.dev1.dist-info/RECORD
gdax_api-1.2.0.dev1.dist-info/WHEEL
gdax_api-1.2.0.dev1.dist-info/metadata.json
gdax_api-1.2.0.dev1.dist-info/top_level.txt
