Metadata-Version: 2.0
Name: gdax-api
Version: 1.2.0.dev1
Summary: GDAX public and authenticated client.
Home-page: https://github.com/Jaewan-Yun/gdax-api-python
Author: Jaewan Yun
Author-email: jay50@pitt.edu
License: MIT
Requires-Dist: requests
